panda_math/__init__.py
panda_math/matrix.py
panda_math/matrix.pyi
panda_math/vector.py
panda_math/vector.pyi
panda_math-0.2.0.1.3.dist-info/licenses/LICENSE
panda_math-0.2.0.1.3.dist-info/METADATA
panda_math-0.2.0.1.3.dist-info/WHEEL
panda_math-0.2.0.1.3.dist-info/top_level.txt
panda_math-0.2.0.1.3.dist-info/RECORD
