Metadata-Version: 2.4
Name: panda-math
Version: 0.2.0.1.3
Summary: A Vector, Matrix, and transformation utilities for 2D, 3D graphics, and game development.
Author-email: Colin Politi <urboycolinthepanda@gmail.com>
License: MIT License
Project-URL: Homepage, https://github.com/ColinThePanda/PandaMath
Project-URL: Bug_Tracker, https://github.com/ColinThePanda/PandaMath/issues
Classifier: Programming Language :: Python :: 3
Classifier: License :: OSI Approved :: MIT License
Classifier: Operating System :: OS Independent
Requires-Python: >=3.9
License-File: LICENSE
Requires-Dist: numpy
Dynamic: license-file
